md2shunn/__init__.py
md2shunn/cli.py
md2shunn-0.9.1.dist-info/METADATA
md2shunn-0.9.1.dist-info/WHEEL
md2shunn-0.9.1.dist-info/entry_points.txt
md2shunn-0.9.1.dist-info/licenses/LICENSE
md2shunn-0.9.1.dist-info/RECORD
